quickapi_async/__init__.py
quickapi_async/core.py
quickapi_async-1.1.0.dist-info/licenses/LICENSE
quickapi_async-1.1.0.dist-info/METADATA
quickapi_async-1.1.0.dist-info/WHEEL
quickapi_async-1.1.0.dist-info/top_level.txt
quickapi_async-1.1.0.dist-info/RECORD
